pycalceff/__init__.py
pycalceff/main.py
pycalceff/cli/__init__.py
pycalceff/cli/commands.py
pycalceff/core/__init__.py
pycalceff/core/cli_utils.py
pycalceff/core/effic.py
pycalceff/data/example_data.txt
pycalceff-1.0.1.dist-info/licenses/LICENSE
pycalceff-1.0.1.dist-info/METADATA
pycalceff-1.0.1.dist-info/WHEEL
pycalceff-1.0.1.dist-info/entry_points.txt
pycalceff-1.0.1.dist-info/top_level.txt
pycalceff-1.0.1.dist-info/RECORD
