Metadata-Version: 2.4
Name: pycalceff
Version: 1.0.1
Summary: Calculate binomial efficiencies and their uncertainties
Author-email: Marc Paterno <paterno@fnal.gov>
License: BSD-3-Clause
Project-URL: Homepage, https://github.com/marcpaterno/pycalceff
Project-URL: Bug Tracker, https://github.com/marcpaterno/pycalceff/issues
Project-URL: Documentation, https://github.com/marcpaterno/pycalceff
Project-URL: Source Code, https://github.com/marcpaterno/pycalceff
Keywords: efficiency,statistics,binomial,confidence-intervals,fermilab
Classifier: Development Status :: 5 - Production/Stable
Classifier: Intended Audience :: Science/Research
Classifier: License :: OSI Approved :: BSD License
Classifier: Operating System :: OS Independent
Classifier: Programming Language :: Python :: 3
Classifier: Programming Language :: Python :: 3.12
Classifier: Programming Language :: Python :: 3.13
Classifier: Programming Language :: Python :: 3.14
Classifier: Topic :: Scientific/Engineering
Classifier: Topic :: Scientific/Engineering :: Physics
Requires-Python: >=3.12
License-File: LICENSE
Requires-Dist: typer
Requires-Dist: rich
Requires-Dist: scipy
Provides-Extra: dev
Requires-Dist: build; extra == "dev"
Requires-Dist: twine; extra == "dev"
Requires-Dist: pytest; extra == "dev"
Requires-Dist: pytest-cov; extra == "dev"
Requires-Dist: pytest-xdist; extra == "dev"
Requires-Dist: mypy; extra == "dev"
Requires-Dist: ruff; extra == "dev"
Requires-Dist: types-setuptools; extra == "dev"
Requires-Dist: scipy-stubs; extra == "dev"
Requires-Dist: hypothesis; extra == "dev"
Requires-Dist: sphinx; extra == "dev"
Requires-Dist: pydata-sphinx-theme; extra == "dev"
Requires-Dist: sphinx-copybutton; extra == "dev"
Dynamic: license-file
